{
    "response": {
        "success": "OPERATION_SUCCESSFUL",
        "validation_error": "MALFORMED_INPUT",
        "auth": {
            "register": {
                "success": "REGISTRATION_SUCCESSFUL"
            },
            "login": {
                "success": "LOGGED_IN",
                "credential_error": "CREDENTIAL_ERROR"
            }
        },
        "containers": {
            "get": {
                "success": "GOT_CONTAINERS"
            },
            "create": {
                "success": "CONTAINER_CREATED",
                "too_many_containers_error": "TOO_MANY_CONTAINERS"
            },
            "delete": {
                "success": "CONTAINER_DELETED",
                "contaier_not_found_error": "CONTAINER_NOT_FOUND"
            },
            "edit": {
                "success": "CONTAINER_EDITED"
            }
        }
    }
}